COPYING
README.rst
setup.py
h5pyd/__init__.py
h5pyd/config.py
h5pyd/h5ds.py
h5pyd/version.py
h5pyd/_apps/__init__.py
h5pyd/_apps/chunkiter.py
h5pyd/_apps/config.py
h5pyd/_apps/hsacl.py
h5pyd/_apps/hsconfigure.py
h5pyd/_apps/hscopy.py
h5pyd/_apps/hsdel.py
h5pyd/_apps/hsdiff.py
h5pyd/_apps/hsget.py
h5pyd/_apps/hsinfo.py
h5pyd/_apps/hsload.py
h5pyd/_apps/hsls.py
h5pyd/_apps/hsmv.py
h5pyd/_apps/hstouch.py
h5pyd/_apps/utillib.py
h5pyd/_hl/__init__.py
h5pyd/_hl/attrs.py
h5pyd/_hl/base.py
h5pyd/_hl/config.py
h5pyd/_hl/dataset.py
h5pyd/_hl/datatype.py
h5pyd/_hl/dims.py
h5pyd/_hl/files.py
h5pyd/_hl/filters.py
h5pyd/_hl/folders.py
h5pyd/_hl/group.py
h5pyd/_hl/h5type.py
h5pyd/_hl/h5type_test.py
h5pyd/_hl/hsdsapp.py
h5pyd/_hl/httpconn.py
h5pyd/_hl/objectid.py
h5pyd/_hl/openid.py
h5pyd/_hl/requests_lambda.py
h5pyd/_hl/selections.py
h5pyd/_hl/serverinfo.py
h5pyd/_hl/table.py
h5pyd_redesign.egg-info/PKG-INFO
h5pyd_redesign.egg-info/SOURCES.txt
h5pyd_redesign.egg-info/dependency_links.txt
h5pyd_redesign.egg-info/entry_points.txt
h5pyd_redesign.egg-info/not-zip-safe
h5pyd_redesign.egg-info/requires.txt
h5pyd_redesign.egg-info/top_level.txt