Metadata-Version: 2.1
Name: h5pyd-redesign
Version: 0.10.3
Summary: h5py compatible client lib for HDF REST API
Home-page: http://github.com/HDFGroup/h5pyd
Author: John Readey
Author-email: jreadey@hdfgrouup.org
License: BSD
License-File: COPYING
